{
  "source": "RunRepeat.com",
  "url": "https://runrepeat.com/how-do-you-masure-up-the-runners-percentile-calculator",
  "dataset": "35 million results from 28,000+ races over 20 years",
  "note": "Percentile indicates the % of runners who are SLOWER than this time. e.g. 10th percentile = faster than 10% of runners (top 90%).",
  "distances": {
    "5K": {
      "overall": {
        "1st": 1120,
        "10th": 1520,
        "20th": 1693,
        "30th": 1826,
        "40th": 1949,
        "50th": 2077,
        "60th": 2218,
        "70th": 2388,
        "80th": 2619,
        "90th": 3004,
        "99th": 4054
      },
      "female": {
        "1st": 1299,
        "10th": 1704,
        "20th": 1869,
        "30th": 1999,
        "40th": 2121,
        "50th": 2248,
        "60th": 2387,
        "70th": 2556,
        "80th": 2783,
        "90th": 3144,
        "99th": 4132
      },
      "male": {
        "1st": 1050,
        "10th": 1406,
        "20th": 1564,
        "30th": 1678,
        "40th": 1781,
        "50th": 1888,
        "60th": 2008,
        "70th": 2155,
        "80th": 2361,
        "90th": 2743,
        "99th": 3931
      }
    },
    "10K": {
      "overall": {
        "1st": 2178,
        "10th": 2891,
        "20th": 3167,
        "30th": 3363,
        "40th": 3545,
        "50th": 3728,
        "60th": 3938,
        "70th": 4208,
        "80th": 4605,
        "90th": 5278,
        "99th": 6975
      },
      "female": {
        "1st": 2472,
        "10th": 3215,
        "20th": 3481,
        "30th": 3662,
        "40th": 3830,
        "50th": 4014,
        "60th": 4238,
        "70th": 4536,
        "80th": 4966,
        "90th": 5594,
        "99th": 7159
      },
      "male": {
        "1st": 2064,
        "10th": 2711,
        "20th": 2977,
        "30th": 3148,
        "40th": 3290,
        "50th": 3435,
        "60th": 3602,
        "70th": 3823,
        "80th": 4153,
        "90th": 4761,
        "99th": 6678
      }
    },
    "half_marathon": {
      "overall": {
        "1st": 5039,
        "10th": 6430,
        "20th": 6972,
        "30th": 7368,
        "40th": 7734,
        "50th": 8099,
        "60th": 8502,
        "70th": 8988,
        "80th": 9665,
        "90th": 10758,
        "99th": 13706
      },
      "female": {
        "1st": 5755,
        "10th": 7021,
        "20th": 7558,
        "30th": 7945,
        "40th": 8290,
        "50th": 8643,
        "60th": 9044,
        "70th": 9545,
        "80th": 10231,
        "90th": 11301,
        "99th": 14041
      },
      "male": {
        "1st": 4717,
        "10th": 6035,
        "20th": 6553,
        "30th": 6903,
        "40th": 7096,
        "50th": 7188,
        "60th": 7798,
        "70th": 8191,
        "80th": 8757,
        "90th": 9768,
        "99th": 13000
      }
    },
    "marathon": {
      "overall": {
        "1st": 10248,
        "10th": 12706,
        "20th": 13793,
        "30th": 14576,
        "40th": 15309,
        "50th": 15993,
        "60th": 16710,
        "70th": 17538,
        "80th": 18660,
        "90th": 20505,
        "99th": 26201
      },
      "female": {
        "1st": 11495,
        "10th": 13762,
        "20th": 14818,
        "30th": 15624,
        "40th": 16281,
        "50th": 16929,
        "60th": 17617,
        "70th": 18456,
        "80th": 19600,
        "90th": 21391,
        "99th": 26756
      },
      "male": {
        "1st": 9858,
        "10th": 12160,
        "20th": 13213,
        "30th": 13987,
        "40th": 14627,
        "50th": 15269,
        "60th": 15933,
        "70th": 16706,
        "80th": 17733,
        "90th": 19526,
        "99th": 25508
      }
    }
  }
}
